{
  "project_info": {
    "project_number": "229927513781",
    "project_id": "textfi",
    "storage_bucket": "textfi.appspot.com"
  },
  "client": [
    {
      "client_info": {
        "mobilesdk_app_id": "1:229927513781:android:1900c62cb6eccda49818fc",
        "android_client_info": {
          "package_name": "com.textfi"
        }
      },
      "oauth_client": [
        {
          "client_id": "229927513781-1jv1svvuf84s40ja4vdd7gg417hpjqn2.apps.googleusercontent.com",
          "client_type": 1,
          "android_info": {
            "package_name": "com.textfi",
            "certificate_hash": "5e8f16062ea3cd2c4a0d547876baa6f38cabf625"
          }
        },
        {
          "client_id": "229927513781-vatlaf2m8go266na0mj7knkpiv2mn4k9.apps.googleusercontent.com",
          "client_type": 3
        }
      ],
      "api_key": [
        {
          "current_key": "AIzaSyAejhG65SFW1-HSOlsCghkfyNpfe_MUzWs"
        }
      ],
      "services": {
        "appinvite_service": {
          "other_platform_oauth_client": [
            {
              "client_id": "229927513781-vatlaf2m8go266na0mj7knkpiv2mn4k9.apps.googleusercontent.com",
              "client_type": 3
            }
          ]
        }
      }
    }
  ],
  "configuration_version": "1"
}